enviroment_name/bin/activate_this.py
enviroment_name/bin/django-admin.py
enviroment_name/bin/rst2html.py
enviroment_name/bin/rst2html4.py
enviroment_name/bin/rst2html5.py
enviroment_name/bin/rst2latex.py
enviroment_name/bin/rst2man.py
enviroment_name/bin/rst2odt.py
enviroment_name/bin/rst2odt_prepstyles.py
enviroment_name/bin/rst2pseudoxml.py
enviroment_name/bin/rst2s5.py
enviroment_name/bin/rst2xetex.py
enviroment_name/bin/rst2xml.py
enviroment_name/bin/rstpep2html.py
openlxp_xia/__init__.py
openlxp_xia/admin.py
openlxp_xia/apps.py
openlxp_xia/models.py
openlxp_xia/urls.py
openlxp_xia/views.py
openlxp_xia/management/__init__.py
openlxp_xia/management/commands/__init__.py
openlxp_xia/management/commands/load_supplemental_metadata.py
openlxp_xia/management/commands/load_target_metadata.py
openlxp_xia/management/commands/transform_source_metadata.py
openlxp_xia/management/commands/validate_source_metadata.py
openlxp_xia/management/commands/validate_target_metadata.py
openlxp_xia/management/utils/__init__.py
openlxp_xia/management/utils/model_help.py
openlxp_xia/management/utils/xia_internal.py
openlxp_xia/management/utils/xis_client.py
openlxp_xia/management/utils/xss_client.py
openlxp_xia/migrations/0001_initial.py
openlxp_xia/migrations/0002_use_xss.py
openlxp_xia/migrations/0003_xisconfiguration_xis_api_key.py
openlxp_xia/migrations/0004_alter_xiaconfiguration_xss_api.py
openlxp_xia/migrations/0005_alter_xisconfiguration_xis_api_key.py
openlxp_xia/migrations/0006_auto_20230907_1642.py
openlxp_xia/migrations/0007_auto_20250219_1719.py
openlxp_xia/migrations/0008_alter_xiaconfiguration_key_fields.py
openlxp_xia/migrations/0009_auto_20250225_1536.py
openlxp_xia/migrations/__init__.py
openlxp_xia/tests/__init__.py
openlxp_xia/tests/test_setup.py
openlxp_xia/tests/test_xia_command_intergration.py
openlxp_xia/tests/test_xia_command_unit.py
openlxp_xia/tests/test_xia_models_integration.py
openlxp_xia/tests/test_xia_models_unit.py
openlxp_xia-1.7.1.dist-info/METADATA
openlxp_xia-1.7.1.dist-info/WHEEL
openlxp_xia-1.7.1.dist-info/top_level.txt
openlxp_xia-1.7.1.dist-info/RECORD
