Metadata-Version: 2.2
Name: openlxp-xia
Version: 1.7.1
Summary: Sample installable XIA
Home-page: https://github.com/OpenLXP/openlxp-xia/
Author: OpenLXP
Author-email: openlxphost@gmail.com
License: MIT
Classifier: Development Status :: 4 - Beta
Classifier: Environment :: Web Environment
Classifier: Framework :: Django :: 3.2
Classifier: Intended Audience :: Developers
Classifier: License :: OSI Approved :: MIT License
Classifier: Operating System :: OS Independent
Classifier: Programming Language :: Python :: 3 :: Only
Classifier: Programming Language :: Python :: 3.7
Classifier: Programming Language :: Python :: Implementation :: CPython
Classifier: Topic :: Software Development :: Libraries :: Application Frameworks
Classifier: Topic :: Software Development :: Libraries :: Python Modules
Requires-Python: >=3.7
Requires-Dist: Django<4.5.0,>=3.2.3
